suffuse_log/__init__.py
suffuse_log/ansi_config.py
suffuse_log/ansi_swatch.py
suffuse_log/suffuse_formatter.py
suffuse_log/test_ansi_config.py
suffuse_log/test_ansi_swatch.py
suffuse_log/test_suffuse_formatter.py
suffuse_log-0.1.dist-info/LICENSE
suffuse_log-0.1.dist-info/METADATA
suffuse_log-0.1.dist-info/WHEEL
suffuse_log-0.1.dist-info/top_level.txt
suffuse_log-0.1.dist-info/RECORD
