Metadata-Version: 2.1
Name: suffuse-log
Version: 0.1
Summary: Log that utilizes ansi-codes to color and stylize log messages. Allows for configurable/conditional styling.    
Home-page: UNKNOWN
Author: Nick Lawrence
Author-email: ncg-l@outlook.com
License: UNKNOWN
Platform: UNKNOWN
Classifier: Programming Language :: Python :: 3.8
Classifier: License :: OSI Approved :: MIT License
License-File: LICENSE
Requires-Dist: colorama (==0.4.4)
